eightball/__init__.py
eightball/evaluation.py
eightball/grid_explore.py
eightball/imputer.py
eightball/model.py
eightball/param_optimization.py
eightball/param_search.py
eightball/preprocessor.py
eightball-0.0.7.dist-info/DESCRIPTION.rst
eightball-0.0.7.dist-info/METADATA
eightball-0.0.7.dist-info/RECORD
eightball-0.0.7.dist-info/WHEEL
eightball-0.0.7.dist-info/metadata.json
eightball-0.0.7.dist-info/top_level.txt
