Metadata-Version: 2.0
Name: eightball
Version: 0.0.7
Summary: A machine learning classification toolbox.
Home-page: UNKNOWN
Author: Adam Hajari
Author-email: adamhajari@gmail.com
License: UNKNOWN
Platform: UNKNOWN
Requires-Dist: scikit-learn (>=0.19.1)
Requires-Dist: pandas (>=0.22.0)
Requires-Dist: numpy (>=1.14.0)
Requires-Dist: matplotlib (>=1.5.1)
Requires-Dist: seaborn (>=0.7.1)
